ffptutils/__init__.py
ffptutils/ffptutils.py
ffptutils/scripts/__init__.py
ffptutils/scripts/csv2ffpt.py
ffptutils/scripts/ffpt2csv.py
tests/__init__.py
tests/test_ffptutils.py
ffptutils-0.1.1.dist-info/LICENSE
ffptutils-0.1.1.dist-info/METADATA
ffptutils-0.1.1.dist-info/WHEEL
ffptutils-0.1.1.dist-info/entry_points.txt
ffptutils-0.1.1.dist-info/top_level.txt
ffptutils-0.1.1.dist-info/RECORD
