Metadata-Version: 2.1
Name: ffptutils
Version: 0.1.1
Summary: a python library that reads and writes Spirent iTest ParameterTree (.ffpt) files
Home-page: https://github.com/sekineh/ffptutils-py
Author: Hideki Sekine
Author-email: sekineh@me.com
License: MIT
Project-URL: Bug Reports, https://github.com/sekineh/ffptutils-py/issues
Project-URL: Source, https://github.com/sekineh/ffptutils-py/
Platform: UNKNOWN
Classifier: Development Status :: 4 - Beta
Classifier: Programming Language :: Python :: 3
Classifier: License :: OSI Approved :: MIT License
Classifier: Intended Audience :: Telecommunications Industry
Classifier: Topic :: Utilities
Requires-Python: >=3.6
Requires-Dist: lxml (==4.6.3)
